slogsec/__init__.py
slogsec/decrypt.py
slogsec/log.py
slogsec/secure.py
slogsec-1.0.0.dist-info/METADATA
slogsec-1.0.0.dist-info/WHEEL
slogsec-1.0.0.dist-info/top_level.txt
slogsec-1.0.0.dist-info/RECORD
