Metadata-Version: 2.1
Name: slogsec
Version: 1.0.0
Summary: The Perfect Fusion of Beauty & Security
Author: ciaorama
Author-email: ciaorama@tutamail.com
License: Apache License 2.0
Requires-Dist: logcrypt>=1.0.0
Requires-Dist: colorlog>=3.0.0
